{
	"configurations" : 
	[
		{
			"directories" : 
			[
				{
					"build" : ".",
					"jsonFile" : "directory-.-Debug-d0094a50bb2071803777.json",
					"minimumCMakeVersion" : 
					{
						"string" : "3.27"
					},
					"projectIndex" : 0,
					"source" : ".",
					"targetIndexes" : 
					[
						0
					]
				}
			],
			"name" : "Debug",
			"projects" : 
			[
				{
					"directoryIndexes" : 
					[
						0
					],
					"name" : "maxHeap",
					"targetIndexes" : 
					[
						0
					]
				}
			],
			"targets" : 
			[
				{
					"directoryIndex" : 0,
					"id" : "maxHeap::@6890427a1f51a3e7e1df",
					"jsonFile" : "target-maxHeap-Debug-ee16e27bbc6eb28ef326.json",
					"name" : "maxHeap",
					"projectIndex" : 0
				}
			]
		}
	],
	"kind" : "codemodel",
	"paths" : 
	{
		"build" : "C:/Users/User/CLionProjects/maxHeap/cmake-build-debug",
		"source" : "C:/Users/User/CLionProjects/maxHeap"
	},
	"version" : 
	{
		"major" : 2,
		"minor" : 6
	}
}
